Alu.v
`timescale 1ns / 1ps
//////////////////////////////////////////////////////////////////////////////////
// Company: 
// Engineer: 
// 
// Create Date: 24.06.2025 18:56:43
// Design Name: 
// Module Name: Alu
// Project Name: 
// Target Devices: 
// Tool Versions: 
// Description: 
// 
// Dependencies: 
// 
// Revision:
// Revision 0.01 - File Created
// Additional Comments:
// 
//////////////////////////////////////////////////////////////////////////////////

module carry_look_ahead_adder #(parameter n = 4)(
 input  [n-1:0] A,B,
 input C_in, 
 output  [n-1:0] Sum,
 output C_out);
 wire [n-1:0] P ,G; 
 wire [n-1:0] C;
 assign P = A^B; 
 assign G = A&B;
assign C[0] = G[0] | (P[0] & C_in);
assign C[1] = G[1] | (P[1] & G[0]) | (P[1] & P[0] & C_in);
assign C[2] = G[2] | (P[2] & G[1]) | (P[2] & P[1] & G[0]) | (P[2] & P[1] & P[0] & C_in);
assign C[3] = G[3] | (P[3] & G[2]) | (P[3] & P[2] & G[1]) | (P[3] & P[2] & P[1] & G[0]) | (P[3] & P[2] & P[1] & P[0] & C_in);

assign C_out = C[3] ;
assign Sum[0]=  P[0] ^ C_in;
genvar i; 
generate
for (i = 1;i<n;i = i+1) begin
 assign Sum[i] = P[i] ^ C[i-1];
end
endgenerate
endmodule
module addition(A,B,Sum,C_out);
input signed [15:0] A,B;
output signed [15:0] Sum;
output signed C_out ;
wire [0:3] C;
carry_look_ahead_adder cla1(A[3:0],B[3:0],1'b0,Sum[3:0],C[0]);
carry_look_ahead_adder cla2(A[7:4],B[7:4],C[0],Sum[7:4],C[1]);
carry_look_ahead_adder cla3(A[11:8],B[11:8],C[1],Sum[11:8],C[2]);
carry_look_ahead_adder cla4(A[15:12],B[15:12],C[2],Sum[15:12],C[3]);
assign C_out = C[3];
endmodule    
 
module subtractor(
 input signed [15:0] A,B,
 output reg  signed [15:0] Result);
 wire [15:0] B_2compliment;
 assign B_2compliment = ~B + 1;
 wire [15:0] Sum;
 wire Carry_out_CLA;
  
 addition add_inst(
   .A(A),
   .B(B_2compliment),
   .Sum(Sum),
   .C_out(Carry_out_CLA));

always @(*) begin
   Result = Sum;
end



endmodule


 module multiplication(
  input signed [15:0] A,B,
  output signed [31:0] Result);
assign Result = A*B;
endmodule 
module restoring_division #(parameter N = 16)(
    input signed [N-1:0] Dividend,
    input signed [N-1:0] Divisor,
    output reg signed [N-1:0] Quotient,
    output reg signed [N-1:0] Remainder
);
    reg [N-1:0] abs_Dividend, abs_Divisor;
    reg [2*N-1:0] Reg;
    reg [N-1:0] D;
    reg sign_Q, sign_R;
    integer i;

    always @(*) begin
        if (Divisor == 0) begin
            Quotient = 0;
            Remainder = 0;
        end else begin
            abs_Dividend = Dividend[N-1] ? -Dividend : Dividend;
            abs_Divisor  = Divisor[N-1] ? -Divisor  : Divisor;
            Reg = { {N{abs_Dividend[N-1]}}, abs_Dividend }; // fixed sign extension
            D = abs_Divisor;

            for (i = 0; i < N; i = i + 1) begin
                Reg = Reg << 1;
                Reg[2*N-1:N] = Reg[2*N-1:N] - D;
                if (Reg[2*N-1]) begin
                    Reg[2*N-1:N] = Reg[2*N-1:N] + D;
                    Reg[0] = 1'b0;
                end else begin
                    Reg[0] = 1'b1;
                end
            end

            sign_Q = Dividend[N-1] ^ Divisor[N-1];
            sign_R = Dividend[N-1];
            Quotient = sign_Q ? -Reg[N-1:0] : Reg[N-1:0];
            Remainder = sign_R ? -Reg[2*N-1:N] : Reg[2*N-1:N];
        end
    end
endmodule


module enhanced_ALU(
  input signed [15:0] A, B,
  input [3:0] operation,
  output reg signed  [31:0] Result,
  output reg [15:0] Remainder,
  output reg  C_out,
  output reg Z,N,C,V
);

  wire [15:0] Result1;
  wire C_out1;
  addition add_inst(.A(A), .B(B), .Sum(Result1), .C_out(C_out1));

  wire [15:0] Result2;
  subtractor sub_inst(.A(A), .B(B), .Result(Result2));

  wire [31:0] Result3;
  multiplication mult_inst(.A(A), .B(B), .Result(Result3));

  wire [15:0] Result4;
  wire [15:0] Remainder1;
  restoring_division div_inst(.Dividend(A), .Divisor(B), .Quotient(Result4), .Remainder(Remainder1));

  always @(*) begin
    case (operation)
      4'b0000: begin // ADD
        Result = {{16{Result1[15]}},Result1};
        C_out = C_out1;
        Remainder = 0;
      end

      4'b0001: begin // SUB
        Result = {{16{Result2[15]}},Result2};
        C_out = 0;
        Remainder = 0;
      end

      4'b0010: begin // MULT
        Result = Result3;
        C_out = 0;
        Remainder = 0;
      end

      4'b0011: begin // DIV
        Result = {{16{Result4[15]}},Result4};
        Remainder = Remainder1;
        C_out = 0;
      end

      4'b0100: begin // AND
        Result = A & B;
        C_out = 0;
        Remainder = 0;
      end

      4'b0101: begin // OR
        Result = A | B;
        C_out = 0;
        Remainder = 0;
      end

      4'b0110: begin // NOR
        Result = ~(A | B);
        C_out = 0;
        Remainder = 0;
      end

      4'b0111: begin // NAND
        Result = ~(A & B);
        C_out = 0;
        Remainder = 0;
      end

      4'b1000: begin // XOR
        Result = A ^ B;
        C_out = 0;
        Remainder = 0;
      end

      4'b1001: begin // XNOR
        Result = ~(A ^ B);
        C_out = 0;
        Remainder = 0;
      end

      4'b1010: begin // LEFT SHIFT
        Result = A << 1;
        C_out = 0;
        Remainder = 0;
      end

      4'b1011: begin // RIGHT SHIFT
        Result = A >> 1;
        C_out = 0;
        Remainder = 0;
      end

      default: begin
        Result = 0;
        C_out = 0;
        Remainder = 0;
      end
    endcase
  end
always @(*) begin
  Z = (Result == 0);
  N = Result[31];

  case(operation)
    4'b0000: begin // ADD
      C = C_out1;
      V = (A[15] == B[15]) && (Result[15] != A[15]);
    end
    4'b0001: begin // SUB
      C = (A < B);
      V = (A[15] != B[15]) && (Result[15] != A[15]);
    end
    default: begin
      C = 0;
      V = 0;
    end
  endcase
end
initial begin
 $dumpfile("sump.vcd");
 $dumpvars(0,enhanced_ALU);
end
endmodule

dump.vcd
$date
	Tue Jul 22 12:28:19 2025
$end
$version
	Icarus Verilog
$end
$timescale
	1ps
$end
$scope module enhanced_ALU $end
$var wire 16 ! A [15:0] $end
$var wire 16 " B [15:0] $end
$var wire 4 # operation [3:0] $end
$var wire 16 $ Result4 [15:0] $end
$var wire 32 % Result3 [31:0] $end
$var wire 16 & Result2 [15:0] $end
$var wire 16 ' Result1 [15:0] $end
$var wire 16 ( Remainder1 [15:0] $end
$var wire 1 ) C_out1 $end
$var reg 1 * C $end
$var reg 1 + C_out $end
$var reg 1 , N $end
$var reg 16 - Remainder [15:0] $end
$var reg 32 . Result [31:0] $end
$var reg 1 / V $end
$var reg 1 0 Z $end
$scope module add_inst $end
$var wire 16 1 A [15:0] $end
$var wire 16 2 B [15:0] $end
$var wire 16 3 Sum [15:0] $end
$var wire 1 ) C_out $end
$var wire 4 4 C [0:3] $end
$scope module cla1 $end
$var wire 4 5 A [3:0] $end
$var wire 4 6 B [3:0] $end
$var wire 1 7 C_in $end
$var wire 4 8 G [3:0] $end
$var wire 4 9 P [3:0] $end
$var wire 4 : Sum [3:0] $end
$var wire 1 ; C_out $end
$var wire 4 < C [3:0] $end
$scope begin genblk1[1] $end
$upscope $end
$scope begin genblk1[2] $end
$upscope $end
$scope begin genblk1[3] $end
$upscope $end
$upscope $end
$scope module cla2 $end
$var wire 4 = A [3:0] $end
$var wire 4 > B [3:0] $end
$var wire 1 ? C_in $end
$var wire 4 @ G [3:0] $end
$var wire 4 A P [3:0] $end
$var wire 4 B Sum [3:0] $end
$var wire 1 C C_out $end
$var wire 4 D C [3:0] $end
$scope begin genblk1[1] $end
$upscope $end
$scope begin genblk1[2] $end
$upscope $end
$scope begin genblk1[3] $end
$upscope $end
$upscope $end
$scope module cla3 $end
$var wire 4 E A [3:0] $end
$var wire 4 F B [3:0] $end
$var wire 1 G C_in $end
$var wire 4 H G [3:0] $end
$var wire 4 I P [3:0] $end
$var wire 4 J Sum [3:0] $end
$var wire 1 K C_out $end
$var wire 4 L C [3:0] $end
$scope begin genblk1[1] $end
$upscope $end
$scope begin genblk1[2] $end
$upscope $end
$scope begin genblk1[3] $end
$upscope $end
$upscope $end
$scope module cla4 $end
$var wire 4 M A [3:0] $end
$var wire 4 N B [3:0] $end
$var wire 1 O C_in $end
$var wire 4 P G [3:0] $end
$var wire 4 Q P [3:0] $end
$var wire 4 R Sum [3:0] $end
$var wire 1 S C_out $end
$var wire 4 T C [3:0] $end
$scope begin genblk1[1] $end
$upscope $end
$scope begin genblk1[2] $end
$upscope $end
$scope begin genblk1[3] $end
$upscope $end
$upscope $end
$upscope $end
$scope module div_inst $end
$var wire 16 U Dividend [15:0] $end
$var wire 16 V Divisor [15:0] $end
$var reg 16 W D [15:0] $end
$var reg 16 X Quotient [15:0] $end
$var reg 32 Y Reg [31:0] $end
$var reg 16 Z Remainder [15:0] $end
$var reg 16 [ abs_Dividend [15:0] $end
$var reg 16 \ abs_Divisor [15:0] $end
$var reg 1 ] sign_Q $end
$var reg 1 ^ sign_R $end
$var integer 32 _ i [31:0] $end
$upscope $end
$scope module mult_inst $end
$var wire 16 ` A [15:0] $end
$var wire 16 a B [15:0] $end
$var wire 32 b Result [31:0] $end
$upscope $end
$scope module sub_inst $end
$var wire 16 c A [15:0] $end
$var wire 16 d B [15:0] $end
$var wire 16 e Sum [15:0] $end
$var wire 1 f Carry_out_CLA $end
$var wire 16 g B_2compliment [15:0] $end
$var reg 16 h Result [15:0] $end
$scope module add_inst $end
$var wire 16 i A [15:0] $end
$var wire 16 j B [15:0] $end
$var wire 16 k Sum [15:0] $end
$var wire 1 f C_out $end
$var wire 4 l C [0:3] $end
$scope module cla1 $end
$var wire 4 m A [3:0] $end
$var wire 4 n B [3:0] $end
$var wire 1 o C_in $end
$var wire 4 p G [3:0] $end
$var wire 4 q P [3:0] $end
$var wire 4 r Sum [3:0] $end
$var wire 1 s C_out $end
$var wire 4 t C [3:0] $end
$scope begin genblk1[1] $end
$upscope $end
$scope begin genblk1[2] $end
$upscope $end
$scope begin genblk1[3] $end
$upscope $end
$upscope $end
$scope module cla2 $end
$var wire 4 u A [3:0] $end
$var wire 4 v B [3:0] $end
$var wire 1 w C_in $end
$var wire 4 x G [3:0] $end
$var wire 4 y P [3:0] $end
$var wire 4 z Sum [3:0] $end
$var wire 1 { C_out $end
$var wire 4 | C [3:0] $end
$scope begin genblk1[1] $end
$upscope $end
$scope begin genblk1[2] $end
$upscope $end
$scope begin genblk1[3] $end
$upscope $end
$upscope $end
$scope module cla3 $end
$var wire 4 } A [3:0] $end
$var wire 4 ~ B [3:0] $end
$var wire 1 !" C_in $end
$var wire 4 "" G [3:0] $end
$var wire 4 #" P [3:0] $end
$var wire 4 $" Sum [3:0] $end
$var wire 1 %" C_out $end
$var wire 4 &" C [3:0] $end
$scope begin genblk1[1] $end
$upscope $end
$scope begin genblk1[2] $end
$upscope $end
$scope begin genblk1[3] $end
$upscope $end
$upscope $end
$scope module cla4 $end
$var wire 4 '" A [3:0] $end
$var wire 4 (" B [3:0] $end
$var wire 1 )" C_in $end
$var wire 4 *" G [3:0] $end
$var wire 4 +" P [3:0] $end
$var wire 4 ," Sum [3:0] $end
$var wire 1 -" C_out $end
$var wire 4 ." C [3:0] $end
$scope begin genblk1[1] $end
$upscope $end
$scope begin genblk1[2] $end
$upscope $end
$scope begin genblk1[3] $end
$upscope $end
$upscope $end
$upscope $end
$upscope $end
$upscope $end
$enddefinitions $end
#0
$dumpvars
bx ."
x-"
bx ,"
bx +"
bx *"
x)"
bx ("
bz '"
bx &"
x%"
bx $"
bx #"
bx ""
x!"
bx ~
bz }
bx |
x{
bx z
bx y
bx x
xw
bx v
bz u
bx t
xs
bx r
bx q
bx p
0o
bx n
bz m
bx l
bx k
bx j
bz i
bx h
bx g
xf
bx e
bz d
bz c
bx b
bz a
bz `
b10000 _
z^
x]
bx \
bx [
bx Z
bx1111111111111111 Y
bx1 X
bx W
bz V
bz U
bx T
xS
bx R
bx Q
bx P
xO
bz N
bz M
bx L
xK
bx J
bx I
bx H
xG
bz F
bz E
bx D
xC
bx B
bx A
bx @
x?
bz >
bz =
bx <
x;
bx :
bx 9
bx 8
07
bz 6
bz 5
bx 4
bx 3
bz 2
bz 1
10
0/
b0 .
b0 -
0,
0+
0*
x)
bx (
bx '
bx &
bx %
bx1 $
bz #
bz "
bz !
$end
#1000
1f
1-"
b1111 ."
b0 ,"
0w
1)"
0s
1!"
1%"
1?
1G
0)
b1011 z
b111 l
1{
1;
1C
0S
b10 $"
1O
b1100 |
b1110 4
1K
b1010110110 &
b1010110110 h
b1111 &"
b11 B
b1101 J
b111 R
b1010110110 e
b1010110110 k
b110 r
b11 t
b111110100110000 '
b111110100110000 3
b0 :
b1111 <
b1111 D
b1111 L
b11 T
b0 q
b11 y
b1100 x
b1101 #"
b10 ""
b1111 +"
b11 n
b1100 v
b10 ~
b1100 ("
b1110 9
b1 8
b1100 A
b11 @
b10 I
b1101 H
b0 Q
b11 P
b11 p
b0 *"
b1101 6
b11 >
b1101 F
b11 N
b1100001011000011 g
b1100001011000011 j
b11 5
b1111 =
b1111 E
b11 M
b1010110110 (
b1010110110 Z
b1 $
b1 X
0^
0]
b10000 _
b11110100111101 W
b10101101100000000000000001 Y
b11110100111101 \
b11111111110011 [
b11 m
b1111 u
b1111 }
b11 '"
1,
00
b11111111111111111100001011001110 .
b1111010011000010001111100111 %
b1111010011000010001111100111 b
b11110100111101 "
b11110100111101 2
b11110100111101 V
b11110100111101 a
b11110100111101 d
b11111111110011 !
b11111111110011 1
b11111111110011 U
b11111111110011 `
b11111111110011 c
b11111111110011 i
b111 #
#4000
1!"
0)"
1{
1O
b101 l
0%"
0?
1K
b110 4
0;
b1110 |
b1111 ."
b111 &"
b100101001000110 &
b100101001000110 h
b110 :
b0 <
b1000 B
b1110 D
b11 J
b1100 L
b110001110000110 '
b110001110000110 3
b110 R
b1 T
b110 r
b0 t
b100 z
b1010 $"
b100101001000110 e
b100101001000110 k
b100 ,"
b110 x
b0 n
b110 v
b11 ~
b1111 ("
b110 9
b0 8
b100 A
b1010 @
b1010 I
b100 H
b101 Q
b0 P
b110 q
b0 p
b1000 y
b101 #"
b1010 +"
b101 *"
b0 6
b1010 >
b1100 F
b0 N
b1111001101100000 g
b1111001101100000 j
b110 5
b1110 =
b110 E
b101 M
b101100100110 (
b101100100110 Z
b110 $
b110 X
b10000 _
b110010100000 W
b1011001001100000000000000110 Y
b110010100000 \
b101011011100110 [
b110 m
b1110 u
b110 }
b101 '"
0,
b10010100000 .
b110010100000 "
b110010100000 2
b110010100000 V
b110010100000 a
b110010100000 d
b100010010010001011111000000 %
b100010010010001011111000000 b
b101011011100110 !
b101011011100110 1
b101011011100110 U
b101011011100110 `
b101011011100110 c
b101011011100110 i
b100 #
#7000
1+
1w
1)"
1?
0O
1*
1)
0!"
1s
1%"
1;
1G
0K
1S
b1011 l
0{
b1101 4
1C
b111 |
b1111 &"
0,
b1101 T
b1001 t
b1111 ."
b1 L
b1000100011100110 &
b1000100011100110 h
b100 :
b1111 <
b1 B
b1111 D
b1010 J
b10101000010100 '
b10101000010100 3
b10 R
b110 r
b1110 z
b1000 $"
b1000100011100110 e
b1000100011100110 k
b1000 ,"
b1001 p
b1001 n
b1111 ~
b1010 ("
b1010 9
b101 8
b1110 A
b1 @
b1001 I
b0 H
b1000 Q
b101 P
b100 q
b1 y
b110 #"
b1001 ""
b111 +"
b1000 *"
b111 6
b1001 >
b0 F
b101 N
b1010111101101001 g
b1010111101101001 j
b1101 5
b111 =
b1001 E
b1101 M
b1101100101111101 (
b1101100101111101 Z
b0 $
b0 X
1^
1]
b10000 _
b101000010010111 W
b100110100000110000000000000000 Y
b101000010010111 \
b10011010000011 [
b1101 m
b111 u
b1001 }
b1101 '"
b10101000010100 .
b101000010010111 "
b101000010010111 2
b101000010010111 V
b101000010010111 a
b101000010010111 d
b11110011111000000101100010111011 %
b11110011111000000101100010111011 b
b1101100101111101 !
b1101100101111101 1
b1101100101111101 U
b1101100101111101 `
b1101100101111101 c
b1101100101111101 i
b0 #
#10000
1!"
1w
1{
0G
1s
b1001 4
0C
0f
b111 D
b1110 l
0-"
b11 ."
b1110 t
b0 L
b10011010011101 .
b1111 T
b1101 |
b100001000100001 &
b100001000100001 h
b1101 :
b1110 <
b1001 B
b110 J
b10011010011101 '
b10011010011101 3
b10 R
b1 r
b10 z
b10 $"
b1101 &"
b100001000100001 e
b100001000100001 k
b100 ,"
b10 p
b10 n
b1100 v
b1101 ~
b0 ("
b1 9
b1110 8
b110 A
b110 I
b1100 Q
b11 P
b1101 q
b1001 y
b100 x
b1001 #"
b100 ""
b11 +"
b0 *"
b1110 6
b11 >
b10 F
b1111 N
b110111000010 g
b110111000010 j
b1111 5
b101 =
b100 E
b11 M
b101100011001 (
b101100011001 Z
b1111111111111101 $
b1111111111111101 X
0^
b10000 _
b110111000010 W
b1011000110010000000000000011 Y
b110111000010 \
b11010001011111 [
b1111 m
b101 u
b100 }
b11 '"
b1111001000111110 "
b1111001000111110 2
b1111001000111110 V
b1111001000111110 a
b1111001000111110 d
b11111101001011110111110100000010 %
b11111101001011110111110100000010 b
b11010001011111 !
b11010001011111 1
b11010001011111 U
b11010001011111 `
b11010001011111 c
b11010001011111 i
#13000
0!"
0{
1f
1O
1-"
0?
1K
1)
0w
0;
b11 4
1S
b11 l
0s
b11 D
b0 |
b0 <
b0 t
b1110 &"
b1001 ."
b110110111111111 &
b110110111111111 h
b11 :
b110 B
b0 J
b1111 L
b11000001100011 '
b11000001100011 3
b11 R
b1100 T
b1111 r
b1111 z
b1101 $"
b110110111111111 e
b110110111111111 k
b110 ,"
b1000 *"
b1110 n
b1110 ~
b1001 ("
b11 9
b0 8
b0 A
b11 @
b1110 I
b1 H
b1010 Q
b100 P
b1111 q
b0 p
b1111 y
b0 x
b1 #"
b1110 ""
b101 +"
b10 6
b1 F
b110 N
b1001111011001110 g
b1001111011001110 j
b1 5
b11 =
b1111 E
b1100 M
b1100111100110001 (
b1100111100110001 Z
b0 $
b0 X
1^
b10000 _
b110000100110010 W
b110000110011110000000000000000 Y
b110000100110010 \
b11000011001111 [
b1 m
b11 u
b1111 }
b1100 '"
0*
0+
b1000011001100 .
b110000100110010 "
b110000100110010 2
b110000100110010 V
b110000100110010 a
b110000100110010 d
b11101101011110000000100010010010 %
b11101101011110000000100010010010 b
b1100111100110001 !
b1100111100110001 1
b1100111100110001 U
b1100111100110001 `
b1100111100110001 c
b1100111100110001 i
b110 #
#16000
1f
1-"
1w
1!"
0)"
0O
1s
1{
b1101 l
0%"
b1 4
0K
b1111 |
b0 &"
b1110 ."
b1100 T
b1111 t
b111111000010 &
b111111000010 h
b100 :
b11 <
b1100 B
b0 D
b101 J
b10 L
b1011010111000100 '
b1011010111000100 3
b1011 R
b10 r
b1100 z
b1111 $"
b111111000010 e
b111111000010 k
b0 ,"
b10 *"
b1111 n
b1111 v
b1100 ~
b10 ("
b10 9
b1 8
b1100 A
b0 @
b1 I
b10 H
b11 Q
b1100 P
b1100 q
b11 p
b11 y
b1100 x
b1110 #"
b0 ""
b1100 +"
b1 6
b0 >
b11 F
b1101 N
b10110011111111 g
b10110011111111 j
b11 5
b1100 =
b10 E
b1110 M
b1110001011000011 (
b1110001011000011 Z
0]
b10000 _
b10110011111111 W
b11101001111010000000000000000 Y
b10110011111111 \
b1110100111101 [
b11 m
b1100 u
b10 }
b1110 '"
b110000111100 .
b1101001100000001 "
b1101001100000001 2
b1101001100000001 V
b1101001100000001 a
b1101001100000001 d
b101001000111001101111000011 %
b101001000111001101111000011 b
b1110001011000011 !
b1110001011000011 1
b1110001011000011 U
b1110001011000011 `
b1110001011000011 c
b1110001011000011 i
#19000
0w
0s
1?
1;
0)
1!"
b1000 4
0S
1{
1)"
b1110 |
b111 l
1%"
b1111 ."
b100 D
b1111 &"
b1000001000011100 &
b1000001000011100 h
b0 :
b1110 <
b1011 B
b100 J
b11 L
b1110010010110000 '
b1110010010110000 3
b1110 R
b11 T
b1100 r
b110 t
b1 z
b10 $"
b1000001000011100 e
b1000001000011100 k
b1000 ,"
b10 ""
b1000 *"
1,
b110 n
b1011 v
b1110 ~
b1100 ("
b1100 9
b10 8
b10 A
b100 @
b10 I
b1 H
b1000 Q
b11 P
b0 q
b110 p
b1101 y
b10 x
b1101 #"
b111 +"
b1010 6
b100 >
b1 F
b11 N
b1100111010110110 g
b1100111010110110 j
b110 5
b110 =
b11 E
b1011 M
b1110010010110000 (
b1110010010110000 Z
b1111111111111111 $
b1111111111111111 X
1]
b10000 _
b11000101001010 W
b11011010100000000000000000001 Y
b11000101001010 \
b100110010011010 [
b110 m
b110 u
b11 }
b1011 '"
00
b1110010010110000 -
b11111111111111111111111111111111 .
b11000101001010 "
b11000101001010 2
b11000101001010 V
b11000101001010 a
b11000101001010 d
b11110001010000000110000101111100 %
b11110001010000000110000101111100 b
b1011001101100110 !
b1011001101100110 1
b1011001101100110 U
b1011001101100110 `
b1011001101100110 c
b1011001101100110 i
b11 #
#22000
0)"
0%"
1f
1O
0!"
1+
1-"
1*
1K
1)
b1 l
0{
b1011 4
1S
b110 |
1/
0,
b1000 <
b11 D
b0 t
b1 &"
b1110 ."
b11010001101 &
b11010001101 h
b101 :
b1100 B
b11 J
b1100 L
b100001111000101 '
b100001111000101 3
b100 R
b1011 T
b1101 r
b1000 z
b110 $"
b11010001101 e
b11010001101 k
b0 ,"
b10 *"
b100 n
b110 v
b1 ~
b110 ("
b101 9
b1000 8
b1011 A
b0 @
b1011 I
b100 H
b11 Q
b1000 P
b1101 q
b0 p
b100 y
b100 #"
b1 ""
b1100 +"
b1100 6
b1001 >
b1110 F
b1001 N
b110000101100100 g
b110000101100100 j
b1001 5
b10 =
b101 E
b1010 M
b1010010100101001 (
b1010010100101001 Z
b0 $
b0 X
0]
b10000 _
b110000101100100 W
b1011010110101110000000000000000 Y
b110000101100100 \
b101101011010111 [
b1001 m
b10 u
b101 }
b1010 '"
b0 -
b100001111000101 .
b1001111010011100 "
b1001111010011100 2
b1001111010011100 V
b1001111010011100 a
b1001111010011100 d
b100010100011101111001011111100 %
b100010100011101111001011111100 b
b1010010100101001 !
b1010010100101001 1
b1010010100101001 U
b1010010100101001 `
b1010010100101001 c
b1010010100101001 i
b0 #
#25000
1G
0O
1!"
0f
1C
b1101 4
0K
1{
b100 l
0-"
b0 ."
b111 &"
b1100 D
b11 L
b1110 T
b1000 |
b111100101011111 &
b111100101011111 h
b1 :
b11 B
b1110 J
b100111000110001 '
b100111000110001 3
b100 R
b1111 r
b101 z
b1001 $"
b111100101011111 e
b111100101011111 k
b111 ,"
1,
b111 n
b1001 v
b101 ~
b1 ("
b1 9
b1010 A
b100 @
b1001 I
b10 H
b1000 Q
b110 P
b1111 q
b101 y
b1000 x
b110 #"
b111 +"
b0 *"
b1001 6
b110 >
b1010 F
b1110 N
b1010110010111 g
b1010110010111 j
b1000 5
b1100 =
b11 E
b110 M
b110101101100 (
b110101101100 Z
b1111111111111100 $
b1111111111111100 X
0^
1]
b10000 _
b1010110010111 W
b1101011011000000000000000100 Y
b1010110010111 \
b110001111001000 [
b1000 m
b1100 u
b11 }
b110 '"
0/
0*
00
0+
b110101101100 -
b11111111111111111111111111111100 .
b1110101001101001 "
b1110101001101001 2
b1110101001101001 V
b1110101001101001 a
b1110101001101001 d
b11110111100101011011110100001000 %
b11110111100101011011110100001000 b
b110001111001000 !
b110001111001000 1
b110001111001000 U
b110001111001000 `
b110001111001000 c
b110001111001000 i
b11 #
#28000
1f
1-"
0)
b1100 4
0S
0w
b101 l
0s
b1100 <
b1 &"
b111 L
b1101100111001 &
b1101100111001 h
b1 :
b111 B
b1001 D
b1000 J
b1000100001110001 '
b1000100001110001 3
b1000 R
b111 T
b1001 r
b100 t
b11 z
b1100 |
b1011 $"
b1101100111001 e
b1101100111001 k
b1 ,"
b1100 ."
b100 n
b110 v
b1001 ~
b1100 ("
b1001 9
b100 8
b100 A
b1001 @
b111 I
b0 H
b110 Q
b1 P
b1 q
b100 p
b1011 y
b100 x
b1000 #"
b1001 +"
b100 *"
b1100 6
b1001 >
b110 F
b11 N
b1100100101100100 g
b1100100101100100 j
b101 5
b1101 =
b1 E
b101 M
b1101100111001 (
b1101100111001 Z
b1 $
b1 X
0]
b10000 _
b11011010011100 W
b11011001110010000000000000001 Y
b11011010011100 \
b101000111010101 [
b101 m
b1101 u
b1 }
b101 '"
0,
b0 -
b110011101001001 .
b11011010011100 "
b11011010011100 2
b11011010011100 V
b11011010011100 a
b11011010011100 d
b10001011101001100101111001100 %
b10001011101001100101111001100 b
b101000111010101 !
b101000111010101 1
b101000111010101 U
b101000111010101 `
b101000111010101 c
b101000111010101 i
b1000 #
#31000
1)"
b111 l
1%"
0?
b100 4
0;
b1 L
b0 <
b0 t
b1111 ."
b0 $"
b1111 &"
b1110 |
b1000000010000111 &
b1000000010000111 h
b11 J
b1111 :
b11 B
b1100 D
b1100001100111111 '
b1100001100111111 3
b1100 R
b10 T
b111 r
b1000 z
b1000000010000111 e
b1000000010000111 k
b1000 ,"
b1111 #"
b0 ""
b0 I
b1 H
b1010 v
b1110 ~
b1101 ("
b1111 9
b0 8
b1011 A
b100 @
b1000 Q
b10 P
b111 q
b0 p
b100 y
b1010 x
b111 +"
b1000 *"
b101 >
b1 F
b10 N
b1101111010100100 g
b1101111010100100 j
b11 5
b1110 =
b1010 M
b1110010010011011 (
b1110010010011011 Z
b1111111111111110 $
b1111111111111110 X
1^
1]
b10000 _
b10000101011100 W
b11011011001010000000000000010 Y
b10000101011100 \
b101111000011101 [
b11 m
b1110 u
b1010 '"
b10000101000000 .
b10000101011100 "
b10000101011100 2
b10000101011100 V
b10000101011100 a
b10000101011100 d
b11110011101111000111000010010100 %
b11110011101111000111000010010100 b
b1010000111100011 !
b1010000111100011 1
b1010000111100011 U
b1010000111100011 `
b1010000111100011 c
b1010000111100011 i
b100 #
#34000
1w
0G
1O
1s
0C
b10 4
1K
0!"
0f
b1000 t
b1011 B
0{
b1010 l
0-"
b1100 &"
b0 D
b1111 L
b1 ."
b0 T
b1 |
b110100101110001 &
b110100101110001 h
b0 J
b1011000010111111 '
b1011000010111111 3
b1011 R
b1 r
b111 z
b1001 $"
b110100101110001 e
b110100101110001 k
b110 ,"
b1000 p
b1001 n
b101 v
b1100 ~
b101 ("
b0 @
b1110 I
b1010 Q
b0 P
b1 q
b100 y
b1 x
b1 #"
b1100 ""
b101 +"
b0 *"
b111 6
b1010 >
b11 F
b1010 N
b101110001011001 g
b101110001011001 j
b1000 5
b1 =
b1101 E
b0 M
b110100011000 (
b110100011000 Z
b0 $
b0 X
0^
b10000 _
b101110001011001 W
b1101000110000000000000000000 Y
b101110001011001 \
b110100011000 [
b1000 m
b1 u
b1101 }
b0 '"
b100000000 .
b1010001110100111 "
b1010001110100111 2
b1010001110100111 V
b1010001110100111 a
b1010001110100111 d
b11111011010001101101001010101000 %
b11111011010001101101001010101000 b
b110100011000 !
b110100011000 1
b110100011000 U
b110100011000 `
b110100011000 c
b110100011000 i
#37000
1)
0!"
1f
1G
1S
0w
0{
0)"
1-"
1C
0O
0s
b1 l
0%"
b101 4
0K
b1100 D
b1 |
b0 &"
b1110 ."
b1101011111101101 &
b1101011111101101 h
b1101 :
b1011 B
b1001 J
b0 L
b100110111101 '
b100110111101 3
b0 R
b1111 T
b1101 r
b0 t
b1110 z
b111 $"
b1101011111101101 e
b1101011111101101 k
b1101 ,"
b1000 n
b1 v
b111 ~
b1110 ("
b1101 9
b11 A
b1100 @
b1000 I
b0 H
b1110 Q
b1 P
b1101 q
b0 p
b1100 y
b1 x
b111 #"
b0 ""
b1 +"
b1110 *"
b1000 6
b1110 >
b1000 F
b1 N
b1110011100011000 g
b1110011100011000 j
b101 5
b1101 =
b0 E
b1111 M
b1111000011010101 (
b1111000011010101 Z
1^
b10000 _
b1100011101000 W
b1111001010110000000000000000 Y
b1100011101000 \
b111100101011 [
b101 m
b1101 u
b0 }
b1111 '"
1,
b11111111111111111110100000111101 .
b1100011101000 "
b1100011101000 2
b1100011101000 V
b1100011101000 a
b1100011101000 d
b11111110100001100011100100001000 %
b11111110100001100011100100001000 b
b1111000011010101 !
b1111000011010101 1
b1111000011010101 U
b1111000011010101 `
b1111000011010101 c
b1111000011010101 i
b1000 #
#40000
0f
1O
1)"
0-"
1G
1K
b10 l
1%"
1C
1)
b111 |
b1100 D
b111 4
1S
b11 ."
b1100100110001111 &
b1100100110001111 h
b1111 :
b1 B
b1 J
b1111 L
b1001000100011111 '
b1001000100011111 3
b1001 R
b1110 T
b1111 r
b1000 z
b1001 $"
b1100 &"
b1100100110001111 e
b1100100110001111 k
b1100 ,"
b11 v
b1100 ~
b1 ("
b1111 9
b1001 A
b100 @
b1110 I
b1 H
b100 Q
b1010 P
b1111 q
b110 y
b1 #"
b1100 ""
b1011 +"
b0 *"
b1100 >
b11 F
b1110 N
b1110000111000 g
b1110000111000 j
b111 5
b101 =
b1101 E
b1010 M
b1110010111000111 (
b1110010111000111 Z
b10 $
b10 X
0]
b10000 _
b1110000111000 W
b11010001110010000000000000010 Y
b1110000111000 \
b101001010101001 [
b111 m
b101 u
b1101 }
b1010 '"
0,
00
b1110010111000111 -
b10 .
b1110001111001000 "
b1110001111001000 2
b1110001111001000 V
b1110001111001000 a
b1110001111001000 d
b1001000111001001000011111000 %
b1001000111001001000011111000 b
b1010110101010111 !
b1010110101010111 1
b1010110101010111 U
b1010110101010111 `
b1010110101010111 c
b1010110101010111 i
b11 #
